README
setup.py
rosci.egg-info/PKG-INFO
rosci.egg-info/SOURCES.txt
rosci.egg-info/dependency_links.txt
rosci.egg-info/requires.txt
rosci.egg-info/top_level.txt
scripts/rosci
scripts/rosci-catkin-depends
scripts/rosci-clean-junit-xml
src/rosci/__init__.py
src/rosci/catkin_support.py
src/rosci/ci_base.py
src/rosci/jenkins_support.py
src/rosci/job_creator.py
src/rosci/junitxml.py
src/rosci/main.py
src/rosci/rosdep_support.py
templates/__init__.py