Metadata-Version: 1.0
Name: rosci
Version: 0.1.2
Summary: rosci continuous integration tool
Home-page: http://www.ros.org/wiki/rosci
Author: Ken Conley
Author-email: kwc@willowgarage.com
License: BSD
Download-URL: http://pr.willowgarage.com/downloads/rosci/
Keywords: ROS
Platform: UNKNOWN
Classifier: Programming Language :: Python
Classifier: License :: OSI Approved :: BSD License
